{
  "games": [
        {
      "names": [
        [
          "en",
          "Diving obby"
        ],
        [
          "ru",
          "Diving obby"
        ],
        [
          "tr",
          "Diving obby"
        ]
      ],
      "imageURL": "https://raw.githubusercontent.com/ygterdem/YG-Medynaes-Games/main/images/divingobby.png",
      "gameid": "371181",
      "pc": true,
      "mobile": true
    },
    {
      "names": [
        [
          "en",
          "Jumping obby"
        ],
        [
          "ru",
          "Jumping obby"
        ],
        [
          "tr",
          "Jumping obby"
        ]
      ],
      "imageURL": "https://raw.githubusercontent.com/ygterdem/YG-Medynaes-Games/main/images/obby.png",
      "gameid": "363419",
      "pc": true,
      "mobile": true
    },
    {
      "names": [
        [
          "en",
          "Route 66"
        ],
        [
          "ru",
         "Route 66"
        ],
        [
          "tr",
          "Route 66"
        ]
      ],
      "imageURL": "https://raw.githubusercontent.com/ygterdem/YG-Medynaes-Games/main/images/route66.png",
      "gameid": "377091",
      "pc": true,
      "mobile": true
    }
    
  ]
}